CMakeLists.txt
LICENSE
MANIFEST.in
README.md
setup.py
cmake/LocatePythonLibs.cmake
cmake/LyconUtils.cmake
lycon/__init__.py
lycon/core.py
lycon/enum.py
lycon.egg-info/PKG-INFO
lycon.egg-info/SOURCES.txt
lycon.egg-info/dependency_links.txt
lycon.egg-info/requires.txt
lycon.egg-info/top_level.txt
lycon.egg-info/zip-safe
src/lycon/arch.h
src/lycon/defs.h
src/lycon/types.h
src/lycon/io/base.cc
src/lycon/io/base.h
src/lycon/io/bitstream.cc
src/lycon/io/bitstream.h
src/lycon/io/exif.cc
src/lycon/io/exif.h
src/lycon/io/io.cc
src/lycon/io/io.h
src/lycon/io/jpeg.cc
src/lycon/io/jpeg.h
src/lycon/io/options.h
src/lycon/io/png.cc
src/lycon/io/png.h
src/lycon/mat/allocator.cc
src/lycon/mat/allocator.h
src/lycon/mat/buffer_pool.h
src/lycon/mat/convert.cc
src/lycon/mat/convert.h
src/lycon/mat/copy.cc
src/lycon/mat/io_array.cc
src/lycon/mat/io_array.h
src/lycon/mat/io_array_impl.h
src/lycon/mat/iterator.cc
src/lycon/mat/iterator.h
src/lycon/mat/iterator_impl.h
src/lycon/mat/mat.cc
src/lycon/mat/mat.h
src/lycon/mat/mat_impl.h
src/lycon/mat/matx.h
src/lycon/mat/shared.h
src/lycon/mat/size.h
src/lycon/mat/step.h
src/lycon/mat/umat_data.cc
src/lycon/mat/umat_data.h
src/lycon/mat/vec.h
src/lycon/python/compat.h
src/lycon/python/gil.h
src/lycon/python/interop.cc
src/lycon/python/interop.h
src/lycon/python/macros.h
src/lycon/python/module.cc
src/lycon/python/module.init.h
src/lycon/python/module.io.h
src/lycon/python/module.transform.h
src/lycon/python/numpy.h
src/lycon/transform/resize.cc
src/lycon/transform/resize.h
src/lycon/transform/rotate.cc
src/lycon/transform/rotate.h
src/lycon/transform/resize/area.h
src/lycon/transform/resize/common.h
src/lycon/transform/resize/cubic.h
src/lycon/transform/resize/interp.lut.h
src/lycon/transform/resize/invoker.h
src/lycon/transform/resize/lanczos.h
src/lycon/transform/resize/linear.h
src/lycon/transform/resize/nearest.h
src/lycon/types/numeric.h
src/lycon/types/point.h
src/lycon/types/range.h
src/lycon/types/rect.h
src/lycon/types/scalar.h
src/lycon/types/size.h
src/lycon/types/traits.h
src/lycon/util/alloc.cc
src/lycon/util/alloc.h
src/lycon/util/auto_buffer.h
src/lycon/util/color.cc
src/lycon/util/color.h
