Metadata-Version: 1.1
Name: lycon
Version: 0.1.9
Summary: A minimal and fast image library
Home-page: https://github.com/ethereon/lycon
Author: Saumitro Dasgupta
Author-email: sd@cs.stanford.edu
License: MIT + 3-clause BSD
Keywords: Imaging
Platform: UNKNOWN
Classifier: Development Status :: 4 - Beta
Classifier: Topic :: Multimedia :: Graphics
Classifier: Programming Language :: Python :: 2
Classifier: Programming Language :: Python :: 2.7
Classifier: Programming Language :: Python :: 3
Classifier: Programming Language :: Python :: 3.3
Classifier: Programming Language :: Python :: 3.4
Classifier: Programming Language :: Python :: 3.5
Classifier: Programming Language :: Python :: 3.6
Classifier: Programming Language :: Python :: Implementation :: CPython
